mcfast/__init__.py
mcfast/mcfast.cpython-312-darwin.so
mcfast-0.1.1.dist-info/METADATA
mcfast-0.1.1.dist-info/WHEEL
mcfast-0.1.1.dist-info/RECORD
