Metadata-Version: 2.4
Name: mcfast
Version: 0.1.1
Classifier: Programming Language :: Rust
Classifier: Programming Language :: Python :: Implementation :: CPython
Classifier: Programming Language :: Python :: Implementation :: PyPy
Requires-Dist: pandas>=2.0.3
Requires-Dist: tqdm>=4.67.1
Summary: A set of utilities and Rust-accelerated functions for the McFACTS AGN disk simulation project
Keywords: astronomy,physics
Author-email: Nicolas Roman Posner <nicolasposner@gmail.com>
Maintainer-email: Nicolas Roman Posner <nicolasposner@gmail.com>
License: MIT
Requires-Python: >=3.8
